[{"gameId":"190324_230814_324012", "totalSteps":1312, "obsequium":0, "porcentaje":0, "bonus":0, "totalReward": "-0.9801", "events":[{"name": "NewRoom", "des": "prev 23 curr 22", "reward": 0.001, "totalReward": -0.00020000000000000394, "version": 1, "timestamp": "2019-03-24 23:08:45.757144", "numDia": 1, "momentoDia": 4, "obsequium": 31, "numPantalla": 23, "pantallaHex": "89", "planta": 0, "guillermoPosX": 133, "guillermoPosY": 159, "bonus": 0, "porcentaje": 0}, {"name": "NewRoom", "des": "prev 22 curr 23", "reward": 0.001, "totalReward": 0.003799999999999996, "version": 1, "timestamp": "2019-03-24 23:08:47.198651", "numDia": 1, "momentoDia": 4, "obsequium": 31, "numPantalla": 22, "pantallaHex": "8A", "planta": 0, "guillermoPosX": 133, "guillermoPosY": 160, "bonus": 0, "porcentaje": 0}, {"name": "NewRoom", "des": "prev 23 curr 22", "reward": 0.001, "totalReward": 0.007799999999999996, "version": 1, "timestamp": "2019-03-24 23:08:48.608119", "numDia": 1, "momentoDia": 4, "obsequium": 31, "numPantalla": 23, "pantallaHex": "89", "planta": 0, "guillermoPosX": 133, "guillermoPosY": 159, "bonus": 0, "porcentaje": 0}, {"name": "NewRoom", "des": "prev 22 curr 21", "reward": 0.001, "totalReward": 0.009200000000000017, "version": 1, "timestamp": "2019-03-24 23:08:55.998486", "numDia": 1, "momentoDia": 4, "obsequium": 31, "numPantalla": 22, "pantallaHex": "88", "planta": 0, "guillermoPosX": 139, "guillermoPosY": 143, "bonus": 0, "porcentaje": 0}, {"name": "NewRoom", "des": "prev 21 curr 23", "reward": 0.001, "totalReward": 0.013000000000000018, "version": 1, "timestamp": "2019-03-24 23:08:58.899181", "numDia": 1, "momentoDia": 4, "obsequium": 31, "numPantalla": 21, "pantallaHex": "8A", "planta": 0, "guillermoPosX": 136, "guillermoPosY": 167, "bonus": 0, "porcentaje": 0}, {"name": "NewRoom", "des": "prev 23 curr 22", "reward": 0.001, "totalReward": 0.01960000000000005, "version": 1, "timestamp": "2019-03-24 23:09:08.498274", "numDia": 1, "momentoDia": 4, "obsequium": 31, "numPantalla": 23, "pantallaHex": "89", "planta": 0, "guillermoPosX": 133, "guillermoPosY": 159, "bonus": 0, "porcentaje": 0}, {"name": "NewRoom", "des": "prev 22 curr 23", "reward": 0.001, "totalReward": 0.02360000000000005, "version": 1, "timestamp": "2019-03-24 23:09:09.904089", "numDia": 1, "momentoDia": 4, "obsequium": 31, "numPantalla": 22, "pantallaHex": "8A", "planta": 0, "guillermoPosX": 134, "guillermoPosY": 160, "bonus": 0, "porcentaje": 0}, {"name": "NewRoom", "des": "prev 23 curr 22", "reward": 0.001, "totalReward": 0.02760000000000005, "version": 1, "timestamp": "2019-03-24 23:09:11.398387", "numDia": 1, "momentoDia": 4, "obsequium": 31, "numPantalla": 23, "pantallaHex": "89", "planta": 0, "guillermoPosX": 134, "guillermoPosY": 159, "bonus": 0, "porcentaje": 0}, {"name": "NewRoom", "des": "prev 22 curr 23", "reward": 0.001, "totalReward": 0.05019999999999903, "version": 1, "timestamp": "2019-03-24 23:10:47.562879", "numDia": 1, "momentoDia": 4, "obsequium": 31, "numPantalla": 22, "pantallaHex": "8A", "planta": 0, "guillermoPosX": 135, "guillermoPosY": 160, "bonus": 0, "porcentaje": 0}, {"name": "NewRoom", "des": "prev 23 curr 22", "reward": 0.001, "totalReward": 0.05589999999999869, "version": 1, "timestamp": "2019-03-24 23:11:09.552335", "numDia": 1, "momentoDia": 4, "obsequium": 31, "numPantalla": 23, "pantallaHex": "89", "planta": 0, "guillermoPosX": 135, "guillermoPosY": 159, "bonus": 0, "porcentaje": 0}, {"name": "NewRoom", "des": "prev 22 curr 23", "reward": 0.001, "totalReward": 0.06059999999999863, "version": 1, "timestamp": "2019-03-24 23:11:13.853235", "numDia": 1, "momentoDia": 4, "obsequium": 31, "numPantalla": 22, "pantallaHex": "8A", "planta": 0, "guillermoPosX": 133, "guillermoPosY": 160, "bonus": 0, "porcentaje": 0}, {"name": "NewRoom", "des": "prev 23 curr 22", "reward": 0.001, "totalReward": 0.06289999999999858, "version": 1, "timestamp": "2019-03-24 23:11:23.401964", "numDia": 1, "momentoDia": 4, "obsequium": 31, "numPantalla": 23, "pantallaHex": "89", "planta": 0, "guillermoPosX": 137, "guillermoPosY": 159, "bonus": 0, "porcentaje": 0}, {"name": "NewRoom", "des": "prev 22 curr 23", "reward": 0.001, "totalReward": 0.06679999999999858, "version": 1, "timestamp": "2019-03-24 23:11:24.797071", "numDia": 1, "momentoDia": 4, "obsequium": 31, "numPantalla": 22, "pantallaHex": "8A", "planta": 0, "guillermoPosX": 137, "guillermoPosY": 160, "bonus": 0, "porcentaje": 0}, {"name": "NewRoom", "des": "prev 23 curr 22", "reward": 0.001, "totalReward": 0.07019999999999857, "version": 1, "timestamp": "2019-03-24 23:11:27.554377", "numDia": 1, "momentoDia": 4, "obsequium": 31, "numPantalla": 23, "pantallaHex": "89", "planta": 0, "guillermoPosX": 139, "guillermoPosY": 157, "bonus": 0, "porcentaje": 0}, {"name": "NewRoom", "des": "prev 22 curr 21", "reward": 0.001, "totalReward": 0.07309999999999849, "version": 1, "timestamp": "2019-03-24 23:11:35.946394", "numDia": 1, "momentoDia": 4, "obsequium": 31, "numPantalla": 22, "pantallaHex": "88", "planta": 0, "guillermoPosX": 135, "guillermoPosY": 143, "bonus": 0, "porcentaje": 0}, {"name": "NewRoom", "des": "prev 21 curr 22", "reward": 0.001, "totalReward": 0.07709999999999849, "version": 1, "timestamp": "2019-03-24 23:11:37.396393", "numDia": 1, "momentoDia": 4, "obsequium": 31, "numPantalla": 21, "pantallaHex": "89", "planta": 0, "guillermoPosX": 134, "guillermoPosY": 145, "bonus": 0, "porcentaje": 0}, {"name": "NewRoom", "des": "prev 22 curr 21", "reward": 0.001, "totalReward": 0.08109999999999849, "version": 1, "timestamp": "2019-03-24 23:11:38.846400", "numDia": 1, "momentoDia": 4, "obsequium": 31, "numPantalla": 22, "pantallaHex": "88", "planta": 0, "guillermoPosX": 134, "guillermoPosY": 143, "bonus": 0, "porcentaje": 0}, {"name": "NewRoom", "des": "prev 21 curr 22", "reward": 0.001, "totalReward": 0.08469999999999848, "version": 1, "timestamp": "2019-03-24 23:11:41.046130", "numDia": 1, "momentoDia": 4, "obsequium": 31, "numPantalla": 21, "pantallaHex": "89", "planta": 0, "guillermoPosX": 133, "guillermoPosY": 145, "bonus": 0, "porcentaje": 0}, {"name": "NewRoom", "des": "prev 22 curr 21", "reward": 0.001, "totalReward": 0.08869999999999849, "version": 1, "timestamp": "2019-03-24 23:11:42.459098", "numDia": 1, "momentoDia": 4, "obsequium": 31, "numPantalla": 22, "pantallaHex": "88", "planta": 0, "guillermoPosX": 133, "guillermoPosY": 143, "bonus": 0, "porcentaje": 0}, {"name": "DecrObsequium", "des": "Obsequium 31 Decr -2", "reward": -0.006, "totalReward": 0.08869999999999849, "version": 1, "timestamp": "2019-03-24 23:11:42.810056", "numDia": 1, "momentoDia": 4, "obsequium": 31, "numPantalla": 22, "pantallaHex": "88", "planta": 0, "guillermoPosX": 133, "guillermoPosY": 143, "bonus": 0, "porcentaje": 0}, {"name": "DecrObsequium", "des": "Obsequium 29 Decr -2", "reward": -0.006, "totalReward": 0.08729999999999848, "version": 1, "timestamp": "2019-03-24 23:11:45.365979", "numDia": 1, "momentoDia": 4, "obsequium": 29, "numPantalla": 21, "pantallaHex": "88", "planta": 0, "guillermoPosX": 137, "guillermoPosY": 140, "bonus": 0, "porcentaje": 0}, {"name": "DecrObsequium", "des": "Obsequium 27 Decr -2", "reward": -0.006, "totalReward": 0.08359999999999845, "version": 1, "timestamp": "2019-03-24 23:11:47.226011", "numDia": 1, "momentoDia": 4, "obsequium": 27, "numPantalla": 21, "pantallaHex": "88", "planta": 0, "guillermoPosX": 136, "guillermoPosY": 140, "bonus": 0, "porcentaje": 0}, {"name": "DecrObsequium", "des": "Obsequium 25 Decr -2", "reward": -0.006, "totalReward": 0.08019999999999844, "version": 1, "timestamp": "2019-03-24 23:11:48.566694", "numDia": 1, "momentoDia": 4, "obsequium": 25, "numPantalla": 21, "pantallaHex": "88", "planta": 0, "guillermoPosX": 136, "guillermoPosY": 138, "bonus": 0, "porcentaje": 0}, {"name": "DecrObsequium", "des": "Obsequium 23 Decr -2", "reward": -0.006, "totalReward": 0.07569999999999842, "version": 1, "timestamp": "2019-03-24 23:11:49.928496", "numDia": 1, "momentoDia": 4, "obsequium": 23, "numPantalla": 21, "pantallaHex": "88", "planta": 0, "guillermoPosX": 132, "guillermoPosY": 134, "bonus": 0, "porcentaje": 0}, {"name": "DecrObsequium", "des": "Obsequium 21 Decr -2", "reward": -0.006, "totalReward": 0.0711999999999984, "version": 1, "timestamp": "2019-03-24 23:11:51.229511", "numDia": 1, "momentoDia": 4, "obsequium": 21, "numPantalla": 21, "pantallaHex": "88", "planta": 0, "guillermoPosX": 130, "guillermoPosY": 133, "bonus": 0, "porcentaje": 0}, {"name": "DecrObsequium", "des": "Obsequium 19 Decr -2", "reward": -0.006, "totalReward": 0.06539999999999838, "version": 1, "timestamp": "2019-03-24 23:11:53.005767", "numDia": 1, "momentoDia": 4, "obsequium": 19, "numPantalla": 21, "pantallaHex": "88", "planta": 0, "guillermoPosX": 130, "guillermoPosY": 133, "bonus": 0, "porcentaje": 0}, {"name": "DecrObsequium", "des": "Obsequium 17 Decr -2", "reward": -0.006, "totalReward": 0.06139999999999835, "version": 1, "timestamp": "2019-03-24 23:11:55.408444", "numDia": 1, "momentoDia": 4, "obsequium": 17, "numPantalla": 21, "pantallaHex": "88", "planta": 0, "guillermoPosX": 129, "guillermoPosY": 133, "bonus": 0, "porcentaje": 0}, {"name": "DecrObsequium", "des": "Obsequium 15 Decr -2", "reward": -0.006, "totalReward": 0.05509999999999832, "version": 1, "timestamp": "2019-03-24 23:11:57.499398", "numDia": 1, "momentoDia": 4, "obsequium": 15, "numPantalla": 21, "pantallaHex": "88", "planta": 0, "guillermoPosX": 129, "guillermoPosY": 134, "bonus": 0, "porcentaje": 0}, {"name": "DecrObsequium", "des": "Obsequium 13 Decr -2", "reward": -0.006, "totalReward": 0.051499999999998304, "version": 1, "timestamp": "2019-03-24 23:11:59.125231", "numDia": 1, "momentoDia": 4, "obsequium": 13, "numPantalla": 21, "pantallaHex": "88", "planta": 0, "guillermoPosX": 129, "guillermoPosY": 133, "bonus": 0, "porcentaje": 0}, {"name": "DecrObsequium", "des": "Obsequium 11 Decr -2", "reward": -0.006, "totalReward": 0.04789999999999829, "version": 1, "timestamp": "2019-03-24 23:12:00.953589", "numDia": 1, "momentoDia": 4, "obsequium": 11, "numPantalla": 21, "pantallaHex": "88", "planta": 0, "guillermoPosX": 129, "guillermoPosY": 133, "bonus": 0, "porcentaje": 0}, {"name": "DecrObsequium", "des": "Obsequium 9 Decr -2", "reward": -0.006, "totalReward": 0.04529999999999828, "version": 1, "timestamp": "2019-03-24 23:12:02.643065", "numDia": 1, "momentoDia": 4, "obsequium": 9, "numPantalla": 21, "pantallaHex": "88", "planta": 0, "guillermoPosX": 129, "guillermoPosY": 133, "bonus": 0, "porcentaje": 0}, {"name": "DecrObsequium", "des": "Obsequium 7 Decr -2", "reward": -0.006, "totalReward": 0.041699999999998266, "version": 1, "timestamp": "2019-03-24 23:12:04.007107", "numDia": 1, "momentoDia": 4, "obsequium": 7, "numPantalla": 21, "pantallaHex": "88", "planta": 0, "guillermoPosX": 130, "guillermoPosY": 134, "bonus": 0, "porcentaje": 0}, {"name": "DecrObsequium", "des": "Obsequium 5 Decr -2", "reward": -0.006, "totalReward": 0.03689999999999825, "version": 1, "timestamp": "2019-03-24 23:12:05.414860", "numDia": 1, "momentoDia": 4, "obsequium": 5, "numPantalla": 21, "pantallaHex": "88", "planta": 0, "guillermoPosX": 129, "guillermoPosY": 134, "bonus": 0, "porcentaje": 0}, {"name": "DecrObsequium", "des": "Obsequium 3 Decr -2", "reward": -0.006, "totalReward": 0.030599999999998236, "version": 1, "timestamp": "2019-03-24 23:12:06.943346", "numDia": 1, "momentoDia": 4, "obsequium": 3, "numPantalla": 21, "pantallaHex": "88", "planta": 0, "guillermoPosX": 129, "guillermoPosY": 134, "bonus": 0, "porcentaje": 0}, {"name": "DecrObsequium", "des": "Obsequium 1 Decr -1", "reward": -0.003, "totalReward": 0.02339999999999824, "version": 1, "timestamp": "2019-03-24 23:12:08.981564", "numDia": 1, "momentoDia": 4, "obsequium": 1, "numPantalla": 21, "pantallaHex": "88", "planta": 0, "guillermoPosX": 129, "guillermoPosY": 133, "bonus": 0, "porcentaje": 0}]}]
[{"gameId":"190324_230814_324012", "totalSteps":1312, "obsequium":0, "porcentaje":0, "bonus":0, "totalReward": "-0.9801", "events":[{"name": "NewRoom", "des": "prev 23 curr 22", "reward": 0.001, "totalReward": -0.00020000000000000394, "version": 1, "timestamp": "2019-03-24 23:08:45.757144", "numDia": 1, "momentoDia": 4, "obsequium": 31, "numPantalla": 23, "pantallaHex": "89", "planta": 0, "guillermoPosX": 133, "guillermoPosY": 159, "bonus": 0, "porcentaje": 0}, {"name": "NewRoom", "des": "prev 22 curr 23", "reward": 0.001, "totalReward": 0.003799999999999996, "version": 1, "timestamp": "2019-03-24 23:08:47.198651", "numDia": 1, "momentoDia": 4, "obsequium": 31, "numPantalla": 22, "pantallaHex": "8A", "planta": 0, "guillermoPosX": 133, "guillermoPosY": 160, "bonus": 0, "porcentaje": 0}, {"name": "NewRoom", "des": "prev 23 curr 22", "reward": 0.001, "totalReward": 0.007799999999999996, "version": 1, "timestamp": "2019-03-24 23:08:48.608119", "numDia": 1, "momentoDia": 4, "obsequium": 31, "numPantalla": 23, "pantallaHex": "89", "planta": 0, "guillermoPosX": 133, "guillermoPosY": 159, "bonus": 0, "porcentaje": 0}, {"name": "NewRoom", "des": "prev 22 curr 21", "reward": 0.001, "totalReward": 0.009200000000000017, "version": 1, "timestamp": "2019-03-24 23:08:55.998486", "numDia": 1, "momentoDia": 4, "obsequium": 31, "numPantalla": 22, "pantallaHex": "88", "planta": 0, "guillermoPosX": 139, "guillermoPosY": 143, "bonus": 0, "porcentaje": 0}, {"name": "NewRoom", "des": "prev 21 curr 23", "reward": 0.001, "totalReward": 0.013000000000000018, "version": 1, "timestamp": "2019-03-24 23:08:58.899181", "numDia": 1, "momentoDia": 4, "obsequium": 31, "numPantalla": 21, "pantallaHex": "8A", "planta": 0, "guillermoPosX": 136, "guillermoPosY": 167, "bonus": 0, "porcentaje": 0}, {"name": "NewRoom", "des": "prev 23 curr 22", "reward": 0.001, "totalReward": 0.01960000000000005, "version": 1, "timestamp": "2019-03-24 23:09:08.498274", "numDia": 1, "momentoDia": 4, "obsequium": 31, "numPantalla": 23, "pantallaHex": "89", "planta": 0, "guillermoPosX": 133, "guillermoPosY": 159, "bonus": 0, "porcentaje": 0}, {"name": "NewRoom", "des": "prev 22 curr 23", "reward": 0.001, "totalReward": 0.02360000000000005, "version": 1, "timestamp": "2019-03-24 23:09:09.904089", "numDia": 1, "momentoDia": 4, "obsequium": 31, "numPantalla": 22, "pantallaHex": "8A", "planta": 0, "guillermoPosX": 134, "guillermoPosY": 160, "bonus": 0, "porcentaje": 0}, {"name": "NewRoom", "des": "prev 23 curr 22", "reward": 0.001, "totalReward": 0.02760000000000005, "version": 1, "timestamp": "2019-03-24 23:09:11.398387", "numDia": 1, "momentoDia": 4, "obsequium": 31, "numPantalla": 23, "pantallaHex": "89", "planta": 0, "guillermoPosX": 134, "guillermoPosY": 159, "bonus": 0, "porcentaje": 0}, {"name": "NewRoom", "des": "prev 22 curr 23", "reward": 0.001, "totalReward": 0.05019999999999903, "version": 1, "timestamp": "2019-03-24 23:10:47.562879", "numDia": 1, "momentoDia": 4, "obsequium": 31, "numPantalla": 22, "pantallaHex": "8A", "planta": 0, "guillermoPosX": 135, "guillermoPosY": 160, "bonus": 0, "porcentaje": 0}, {"name": "NewRoom", "des": "prev 23 curr 22", "reward": 0.001, "totalReward": 0.05589999999999869, "version": 1, "timestamp": "2019-03-24 23:11:09.552335", "numDia": 1, "momentoDia": 4, "obsequium": 31, "numPantalla": 23, "pantallaHex": "89", "planta": 0, "guillermoPosX": 135, "guillermoPosY": 159, "bonus": 0, "porcentaje": 0}, {"name": "NewRoom", "des": "prev 22 curr 23", "reward": 0.001, "totalReward": 0.06059999999999863, "version": 1, "timestamp": "2019-03-24 23:11:13.853235", "numDia": 1, "momentoDia": 4, "obsequium": 31, "numPantalla": 22, "pantallaHex": "8A", "planta": 0, "guillermoPosX": 133, "guillermoPosY": 160, "bonus": 0, "porcentaje": 0}, {"name": "NewRoom", "des": "prev 23 curr 22", "reward": 0.001, "totalReward": 0.06289999999999858, "version": 1, "timestamp": "2019-03-24 23:11:23.401964", "numDia": 1, "momentoDia": 4, "obsequium": 31, "numPantalla": 23, "pantallaHex": "89", "planta": 0, "guillermoPosX": 137, "guillermoPosY": 159, "bonus": 0, "porcentaje": 0}, {"name": "NewRoom", "des": "prev 22 curr 23", "reward": 0.001, "totalReward": 0.06679999999999858, "version": 1, "timestamp": "2019-03-24 23:11:24.797071", "numDia": 1, "momentoDia": 4, "obsequium": 31, "numPantalla": 22, "pantallaHex": "8A", "planta": 0, "guillermoPosX": 137, "guillermoPosY": 160, "bonus": 0, "porcentaje": 0}, {"name": "NewRoom", "des": "prev 23 curr 22", "reward": 0.001, "totalReward": 0.07019999999999857, "version": 1, "timestamp": "2019-03-24 23:11:27.554377", "numDia": 1, "momentoDia": 4, "obsequium": 31, "numPantalla": 23, "pantallaHex": "89", "planta": 0, "guillermoPosX": 139, "guillermoPosY": 157, "bonus": 0, "porcentaje": 0}, {"name": "NewRoom", "des": "prev 22 curr 21", "reward": 0.001, "totalReward": 0.07309999999999849, "version": 1, "timestamp": "2019-03-24 23:11:35.946394", "numDia": 1, "momentoDia": 4, "obsequium": 31, "numPantalla": 22, "pantallaHex": "88", "planta": 0, "guillermoPosX": 135, "guillermoPosY": 143, "bonus": 0, "porcentaje": 0}, {"name": "NewRoom", "des": "prev 21 curr 22", "reward": 0.001, "totalReward": 0.07709999999999849, "version": 1, "timestamp": "2019-03-24 23:11:37.396393", "numDia": 1, "momentoDia": 4, "obsequium": 31, "numPantalla": 21, "pantallaHex": "89", "planta": 0, "guillermoPosX": 134, "guillermoPosY": 145, "bonus": 0, "porcentaje": 0}, {"name": "NewRoom", "des": "prev 22 curr 21", "reward": 0.001, "totalReward": 0.08109999999999849, "version": 1, "timestamp": "2019-03-24 23:11:38.846400", "numDia": 1, "momentoDia": 4, "obsequium": 31, "numPantalla": 22, "pantallaHex": "88", "planta": 0, "guillermoPosX": 134, "guillermoPosY": 143, "bonus": 0, "porcentaje": 0}, {"name": "NewRoom", "des": "prev 21 curr 22", "reward": 0.001, "totalReward": 0.08469999999999848, "version": 1, "timestamp": "2019-03-24 23:11:41.046130", "numDia": 1, "momentoDia": 4, "obsequium": 31, "numPantalla": 21, "pantallaHex": "89", "planta": 0, "guillermoPosX": 133, "guillermoPosY": 145, "bonus": 0, "porcentaje": 0}, {"name": "NewRoom", "des": "prev 22 curr 21", "reward": 0.001, "totalReward": 0.08869999999999849, "version": 1, "timestamp": "2019-03-24 23:11:42.459098", "numDia": 1, "momentoDia": 4, "obsequium": 31, "numPantalla": 22, "pantallaHex": "88", "planta": 0, "guillermoPosX": 133, "guillermoPosY": 143, "bonus": 0, "porcentaje": 0}, {"name": "DecrObsequium", "des": "Obsequium 31 Decr -2", "reward": -0.006, "totalReward": 0.08869999999999849, "version": 1, "timestamp": "2019-03-24 23:11:42.810056", "numDia": 1, "momentoDia": 4, "obsequium": 31, "numPantalla": 22, "pantallaHex": "88", "planta": 0, "guillermoPosX": 133, "guillermoPosY": 143, "bonus": 0, "porcentaje": 0}, {"name": "DecrObsequium", "des": "Obsequium 29 Decr -2", "reward": -0.006, "totalReward": 0.08729999999999848, "version": 1, "timestamp": "2019-03-24 23:11:45.365979", "numDia": 1, "momentoDia": 4, "obsequium": 29, "numPantalla": 21, "pantallaHex": "88", "planta": 0, "guillermoPosX": 137, "guillermoPosY": 140, "bonus": 0, "porcentaje": 0}, {"name": "DecrObsequium", "des": "Obsequium 27 Decr -2", "reward": -0.006, "totalReward": 0.08359999999999845, "version": 1, "timestamp": "2019-03-24 23:11:47.226011", "numDia": 1, "momentoDia": 4, "obsequium": 27, "numPantalla": 21, "pantallaHex": "88", "planta": 0, "guillermoPosX": 136, "guillermoPosY": 140, "bonus": 0, "porcentaje": 0}, {"name": "DecrObsequium", "des": "Obsequium 25 Decr -2", "reward": -0.006, "totalReward": 0.08019999999999844, "version": 1, "timestamp": "2019-03-24 23:11:48.566694", "numDia": 1, "momentoDia": 4, "obsequium": 25, "numPantalla": 21, "pantallaHex": "88", "planta": 0, "guillermoPosX": 136, "guillermoPosY": 138, "bonus": 0, "porcentaje": 0}, {"name": "DecrObsequium", "des": "Obsequium 23 Decr -2", "reward": -0.006, "totalReward": 0.07569999999999842, "version": 1, "timestamp": "2019-03-24 23:11:49.928496", "numDia": 1, "momentoDia": 4, "obsequium": 23, "numPantalla": 21, "pantallaHex": "88", "planta": 0, "guillermoPosX": 132, "guillermoPosY": 134, "bonus": 0, "porcentaje": 0}, {"name": "DecrObsequium", "des": "Obsequium 21 Decr -2", "reward": -0.006, "totalReward": 0.0711999999999984, "version": 1, "timestamp": "2019-03-24 23:11:51.229511", "numDia": 1, "momentoDia": 4, "obsequium": 21, "numPantalla": 21, "pantallaHex": "88", "planta": 0, "guillermoPosX": 130, "guillermoPosY": 133, "bonus": 0, "porcentaje": 0}, {"name": "DecrObsequium", "des": "Obsequium 19 Decr -2", "reward": -0.006, "totalReward": 0.06539999999999838, "version": 1, "timestamp": "2019-03-24 23:11:53.005767", "numDia": 1, "momentoDia": 4, "obsequium": 19, "numPantalla": 21, "pantallaHex": "88", "planta": 0, "guillermoPosX": 130, "guillermoPosY": 133, "bonus": 0, "porcentaje": 0}, {"name": "DecrObsequium", "des": "Obsequium 17 Decr -2", "reward": -0.006, "totalReward": 0.06139999999999835, "version": 1, "timestamp": "2019-03-24 23:11:55.408444", "numDia": 1, "momentoDia": 4, "obsequium": 17, "numPantalla": 21, "pantallaHex": "88", "planta": 0, "guillermoPosX": 129, "guillermoPosY": 133, "bonus": 0, "porcentaje": 0}, {"name": "DecrObsequium", "des": "Obsequium 15 Decr -2", "reward": -0.006, "totalReward": 0.05509999999999832, "version": 1, "timestamp": "2019-03-24 23:11:57.499398", "numDia": 1, "momentoDia": 4, "obsequium": 15, "numPantalla": 21, "pantallaHex": "88", "planta": 0, "guillermoPosX": 129, "guillermoPosY": 134, "bonus": 0, "porcentaje": 0}, {"name": "DecrObsequium", "des": "Obsequium 13 Decr -2", "reward": -0.006, "totalReward": 0.051499999999998304, "version": 1, "timestamp": "2019-03-24 23:11:59.125231", "numDia": 1, "momentoDia": 4, "obsequium": 13, "numPantalla": 21, "pantallaHex": "88", "planta": 0, "guillermoPosX": 129, "guillermoPosY": 133, "bonus": 0, "porcentaje": 0}, {"name": "DecrObsequium", "des": "Obsequium 11 Decr -2", "reward": -0.006, "totalReward": 0.04789999999999829, "version": 1, "timestamp": "2019-03-24 23:12:00.953589", "numDia": 1, "momentoDia": 4, "obsequium": 11, "numPantalla": 21, "pantallaHex": "88", "planta": 0, "guillermoPosX": 129, "guillermoPosY": 133, "bonus": 0, "porcentaje": 0}, {"name": "DecrObsequium", "des": "Obsequium 9 Decr -2", "reward": -0.006, "totalReward": 0.04529999999999828, "version": 1, "timestamp": "2019-03-24 23:12:02.643065", "numDia": 1, "momentoDia": 4, "obsequium": 9, "numPantalla": 21, "pantallaHex": "88", "planta": 0, "guillermoPosX": 129, "guillermoPosY": 133, "bonus": 0, "porcentaje": 0}, {"name": "DecrObsequium", "des": "Obsequium 7 Decr -2", "reward": -0.006, "totalReward": 0.041699999999998266, "version": 1, "timestamp": "2019-03-24 23:12:04.007107", "numDia": 1, "momentoDia": 4, "obsequium": 7, "numPantalla": 21, "pantallaHex": "88", "planta": 0, "guillermoPosX": 130, "guillermoPosY": 134, "bonus": 0, "porcentaje": 0}, {"name": "DecrObsequium", "des": "Obsequium 5 Decr -2", "reward": -0.006, "totalReward": 0.03689999999999825, "version": 1, "timestamp": "2019-03-24 23:12:05.414860", "numDia": 1, "momentoDia": 4, "obsequium": 5, "numPantalla": 21, "pantallaHex": "88", "planta": 0, "guillermoPosX": 129, "guillermoPosY": 134, "bonus": 0, "porcentaje": 0}, {"name": "DecrObsequium", "des": "Obsequium 3 Decr -2", "reward": -0.006, "totalReward": 0.030599999999998236, "version": 1, "timestamp": "2019-03-24 23:12:06.943346", "numDia": 1, "momentoDia": 4, "obsequium": 3, "numPantalla": 21, "pantallaHex": "88", "planta": 0, "guillermoPosX": 129, "guillermoPosY": 134, "bonus": 0, "porcentaje": 0}, {"name": "DecrObsequium", "des": "Obsequium 1 Decr -1", "reward": -0.003, "totalReward": 0.02339999999999824, "version": 1, "timestamp": "2019-03-24 23:12:08.981564", "numDia": 1, "momentoDia": 4, "obsequium": 1, "numPantalla": 21, "pantallaHex": "88", "planta": 0, "guillermoPosX": 129, "guillermoPosY": 133, "bonus": 0, "porcentaje": 0}]}]
