[{"gameId":"190323_113650_212486", "totalSteps":169, "obsequium":0, "porcentaje":0, "bonus":0, "totalReward": "-1.0459", "events":[{"name": "NewRoom", "des": "prev 22 curr 21", "reward": 0.001, "totalReward": -0.0001, "version": 1, "timestamp": "2019-03-23 11:36:55.441987", "numDia": 1, "momentoDia": 4, "obsequium": 29, "numPantalla": 22, "pantallaHex": "88", "planta": 0, "guillermoPosX": 134, "guillermoPosY": 143, "bonus": 0, "porcentaje": 0}, {"name": "NewRoom", "des": "prev 21 curr 22", "reward": 0.001, "totalReward": 0.0049, "version": 1, "timestamp": "2019-03-23 11:36:56.730288", "numDia": 1, "momentoDia": 4, "obsequium": 29, "numPantalla": 21, "pantallaHex": "89", "planta": 0, "guillermoPosX": 134, "guillermoPosY": 145, "bonus": 0, "porcentaje": 0}, {"name": "DecrObsequium", "des": "Obsequium 29 Decr -2", "reward": -0.006, "totalReward": 0.008300000000000004, "version": 1, "timestamp": "2019-03-23 11:36:57.595885", "numDia": 1, "momentoDia": 4, "obsequium": 29, "numPantalla": 22, "pantallaHex": "89", "planta": 0, "guillermoPosX": 133, "guillermoPosY": 147, "bonus": 0, "porcentaje": 0}, {"name": "NewRoom", "des": "prev 22 curr 21", "reward": 0.001, "totalReward": 0.0017000000000000038, "version": 1, "timestamp": "2019-03-23 11:36:58.701442", "numDia": 1, "momentoDia": 4, "obsequium": 27, "numPantalla": 22, "pantallaHex": "88", "planta": 0, "guillermoPosX": 133, "guillermoPosY": 143, "bonus": 0, "porcentaje": 0}, {"name": "NewRoom", "des": "prev 21 curr 22", "reward": 0.001, "totalReward": 0.0062, "version": 1, "timestamp": "2019-03-23 11:37:01.216771", "numDia": 1, "momentoDia": 4, "obsequium": 27, "numPantalla": 21, "pantallaHex": "89", "planta": 0, "guillermoPosX": 135, "guillermoPosY": 145, "bonus": 0, "porcentaje": 0}, {"name": "DecrObsequium", "des": "Obsequium 27 Decr -2", "reward": -0.006, "totalReward": 0.010100000000000001, "version": 1, "timestamp": "2019-03-23 11:37:01.865604", "numDia": 1, "momentoDia": 4, "obsequium": 27, "numPantalla": 22, "pantallaHex": "89", "planta": 0, "guillermoPosX": 135, "guillermoPosY": 145, "bonus": 0, "porcentaje": 0}, {"name": "NewRoom", "des": "prev 22 curr 21", "reward": 0.001, "totalReward": 0.004100000000000001, "version": 1, "timestamp": "2019-03-23 11:37:02.830680", "numDia": 1, "momentoDia": 4, "obsequium": 25, "numPantalla": 22, "pantallaHex": "88", "planta": 0, "guillermoPosX": 135, "guillermoPosY": 143, "bonus": 0, "porcentaje": 0}, {"name": "DecrObsequium", "des": "Obsequium 25 Decr -2", "reward": -0.006, "totalReward": 0.010900000000000003, "version": 1, "timestamp": "2019-03-23 11:37:03.844724", "numDia": 1, "momentoDia": 4, "obsequium": 25, "numPantalla": 21, "pantallaHex": "88", "planta": 0, "guillermoPosX": 136, "guillermoPosY": 139, "bonus": 0, "porcentaje": 0}, {"name": "DecrObsequium", "des": "Obsequium 23 Decr -2", "reward": -0.006, "totalReward": 0.007100000000000001, "version": 1, "timestamp": "2019-03-23 11:37:05.353209", "numDia": 1, "momentoDia": 4, "obsequium": 23, "numPantalla": 21, "pantallaHex": "88", "planta": 0, "guillermoPosX": 135, "guillermoPosY": 134, "bonus": 0, "porcentaje": 0}, {"name": "DecrObsequium", "des": "Obsequium 21 Decr -2", "reward": -0.006, "totalReward": 0.004600000000000002, "version": 1, "timestamp": "2019-03-23 11:37:06.596150", "numDia": 1, "momentoDia": 4, "obsequium": 21, "numPantalla": 21, "pantallaHex": "88", "planta": 0, "guillermoPosX": 133, "guillermoPosY": 135, "bonus": 0, "porcentaje": 0}, {"name": "DecrObsequium", "des": "Obsequium 19 Decr -2", "reward": -0.006, "totalReward": -0.0004999999999999986, "version": 1, "timestamp": "2019-03-23 11:37:08.203885", "numDia": 1, "momentoDia": 4, "obsequium": 19, "numPantalla": 21, "pantallaHex": "88", "planta": 0, "guillermoPosX": 132, "guillermoPosY": 134, "bonus": 0, "porcentaje": 0}, {"name": "DecrObsequium", "des": "Obsequium 17 Decr -2", "reward": -0.006, "totalReward": -0.006400000000000001, "version": 1, "timestamp": "2019-03-23 11:37:09.668697", "numDia": 1, "momentoDia": 4, "obsequium": 17, "numPantalla": 21, "pantallaHex": "88", "planta": 0, "guillermoPosX": 129, "guillermoPosY": 134, "bonus": 0, "porcentaje": 0}, {"name": "DecrObsequium", "des": "Obsequium 15 Decr -2", "reward": -0.006, "totalReward": -0.011099999999999995, "version": 1, "timestamp": "2019-03-23 11:37:11.003596", "numDia": 1, "momentoDia": 4, "obsequium": 15, "numPantalla": 21, "pantallaHex": "88", "planta": 0, "guillermoPosX": 129, "guillermoPosY": 134, "bonus": 0, "porcentaje": 0}, {"name": "DecrObsequium", "des": "Obsequium 13 Decr -2", "reward": -0.006, "totalReward": -0.014599999999999991, "version": 1, "timestamp": "2019-03-23 11:37:12.355335", "numDia": 1, "momentoDia": 4, "obsequium": 13, "numPantalla": 21, "pantallaHex": "88", "planta": 0, "guillermoPosX": 129, "guillermoPosY": 134, "bonus": 0, "porcentaje": 0}, {"name": "DecrObsequium", "des": "Obsequium 11 Decr -2", "reward": -0.006, "totalReward": -0.019299999999999987, "version": 1, "timestamp": "2019-03-23 11:37:13.746594", "numDia": 1, "momentoDia": 4, "obsequium": 11, "numPantalla": 21, "pantallaHex": "88", "planta": 0, "guillermoPosX": 129, "guillermoPosY": 134, "bonus": 0, "porcentaje": 0}, {"name": "DecrObsequium", "des": "Obsequium 9 Decr -2", "reward": -0.006, "totalReward": -0.023999999999999983, "version": 1, "timestamp": "2019-03-23 11:37:15.028110", "numDia": 1, "momentoDia": 4, "obsequium": 9, "numPantalla": 21, "pantallaHex": "88", "planta": 0, "guillermoPosX": 130, "guillermoPosY": 134, "bonus": 0, "porcentaje": 0}, {"name": "DecrObsequium", "des": "Obsequium 7 Decr -2", "reward": -0.006, "totalReward": -0.02939999999999998, "version": 1, "timestamp": "2019-03-23 11:37:15.812771", "numDia": 1, "momentoDia": 4, "obsequium": 7, "numPantalla": 21, "pantallaHex": "88", "planta": 0, "guillermoPosX": 130, "guillermoPosY": 133, "bonus": 0, "porcentaje": 0}, {"name": "DecrObsequium", "des": "Obsequium 5 Decr -2", "reward": -0.006, "totalReward": -0.0352, "version": 1, "timestamp": "2019-03-23 11:37:17.003430", "numDia": 1, "momentoDia": 4, "obsequium": 5, "numPantalla": 21, "pantallaHex": "88", "planta": 0, "guillermoPosX": 129, "guillermoPosY": 134, "bonus": 0, "porcentaje": 0}, {"name": "DecrObsequium", "des": "Obsequium 3 Decr -2", "reward": -0.006, "totalReward": -0.039800000000000016, "version": 1, "timestamp": "2019-03-23 11:37:18.271172", "numDia": 1, "momentoDia": 4, "obsequium": 3, "numPantalla": 21, "pantallaHex": "88", "planta": 0, "guillermoPosX": 129, "guillermoPosY": 134, "bonus": 0, "porcentaje": 0}, {"name": "DecrObsequium", "des": "Obsequium 1 Decr -1", "reward": -0.003, "totalReward": -0.044600000000000035, "version": 1, "timestamp": "2019-03-23 11:37:19.829940", "numDia": 1, "momentoDia": 4, "obsequium": 1, "numPantalla": 21, "pantallaHex": "88", "planta": 0, "guillermoPosX": 129, "guillermoPosY": 134, "bonus": 0, "porcentaje": 0}]}]
[{"gameId":"190323_113650_212486", "totalSteps":169, "obsequium":0, "porcentaje":0, "bonus":0, "totalReward": "-1.0459", "events":[{"name": "NewRoom", "des": "prev 22 curr 21", "reward": 0.001, "totalReward": -0.0001, "version": 1, "timestamp": "2019-03-23 11:36:55.441987", "numDia": 1, "momentoDia": 4, "obsequium": 29, "numPantalla": 22, "pantallaHex": "88", "planta": 0, "guillermoPosX": 134, "guillermoPosY": 143, "bonus": 0, "porcentaje": 0}, {"name": "NewRoom", "des": "prev 21 curr 22", "reward": 0.001, "totalReward": 0.0049, "version": 1, "timestamp": "2019-03-23 11:36:56.730288", "numDia": 1, "momentoDia": 4, "obsequium": 29, "numPantalla": 21, "pantallaHex": "89", "planta": 0, "guillermoPosX": 134, "guillermoPosY": 145, "bonus": 0, "porcentaje": 0}, {"name": "DecrObsequium", "des": "Obsequium 29 Decr -2", "reward": -0.006, "totalReward": 0.008300000000000004, "version": 1, "timestamp": "2019-03-23 11:36:57.595885", "numDia": 1, "momentoDia": 4, "obsequium": 29, "numPantalla": 22, "pantallaHex": "89", "planta": 0, "guillermoPosX": 133, "guillermoPosY": 147, "bonus": 0, "porcentaje": 0}, {"name": "NewRoom", "des": "prev 22 curr 21", "reward": 0.001, "totalReward": 0.0017000000000000038, "version": 1, "timestamp": "2019-03-23 11:36:58.701442", "numDia": 1, "momentoDia": 4, "obsequium": 27, "numPantalla": 22, "pantallaHex": "88", "planta": 0, "guillermoPosX": 133, "guillermoPosY": 143, "bonus": 0, "porcentaje": 0}, {"name": "NewRoom", "des": "prev 21 curr 22", "reward": 0.001, "totalReward": 0.0062, "version": 1, "timestamp": "2019-03-23 11:37:01.216771", "numDia": 1, "momentoDia": 4, "obsequium": 27, "numPantalla": 21, "pantallaHex": "89", "planta": 0, "guillermoPosX": 135, "guillermoPosY": 145, "bonus": 0, "porcentaje": 0}, {"name": "DecrObsequium", "des": "Obsequium 27 Decr -2", "reward": -0.006, "totalReward": 0.010100000000000001, "version": 1, "timestamp": "2019-03-23 11:37:01.865604", "numDia": 1, "momentoDia": 4, "obsequium": 27, "numPantalla": 22, "pantallaHex": "89", "planta": 0, "guillermoPosX": 135, "guillermoPosY": 145, "bonus": 0, "porcentaje": 0}, {"name": "NewRoom", "des": "prev 22 curr 21", "reward": 0.001, "totalReward": 0.004100000000000001, "version": 1, "timestamp": "2019-03-23 11:37:02.830680", "numDia": 1, "momentoDia": 4, "obsequium": 25, "numPantalla": 22, "pantallaHex": "88", "planta": 0, "guillermoPosX": 135, "guillermoPosY": 143, "bonus": 0, "porcentaje": 0}, {"name": "DecrObsequium", "des": "Obsequium 25 Decr -2", "reward": -0.006, "totalReward": 0.010900000000000003, "version": 1, "timestamp": "2019-03-23 11:37:03.844724", "numDia": 1, "momentoDia": 4, "obsequium": 25, "numPantalla": 21, "pantallaHex": "88", "planta": 0, "guillermoPosX": 136, "guillermoPosY": 139, "bonus": 0, "porcentaje": 0}, {"name": "DecrObsequium", "des": "Obsequium 23 Decr -2", "reward": -0.006, "totalReward": 0.007100000000000001, "version": 1, "timestamp": "2019-03-23 11:37:05.353209", "numDia": 1, "momentoDia": 4, "obsequium": 23, "numPantalla": 21, "pantallaHex": "88", "planta": 0, "guillermoPosX": 135, "guillermoPosY": 134, "bonus": 0, "porcentaje": 0}, {"name": "DecrObsequium", "des": "Obsequium 21 Decr -2", "reward": -0.006, "totalReward": 0.004600000000000002, "version": 1, "timestamp": "2019-03-23 11:37:06.596150", "numDia": 1, "momentoDia": 4, "obsequium": 21, "numPantalla": 21, "pantallaHex": "88", "planta": 0, "guillermoPosX": 133, "guillermoPosY": 135, "bonus": 0, "porcentaje": 0}, {"name": "DecrObsequium", "des": "Obsequium 19 Decr -2", "reward": -0.006, "totalReward": -0.0004999999999999986, "version": 1, "timestamp": "2019-03-23 11:37:08.203885", "numDia": 1, "momentoDia": 4, "obsequium": 19, "numPantalla": 21, "pantallaHex": "88", "planta": 0, "guillermoPosX": 132, "guillermoPosY": 134, "bonus": 0, "porcentaje": 0}, {"name": "DecrObsequium", "des": "Obsequium 17 Decr -2", "reward": -0.006, "totalReward": -0.006400000000000001, "version": 1, "timestamp": "2019-03-23 11:37:09.668697", "numDia": 1, "momentoDia": 4, "obsequium": 17, "numPantalla": 21, "pantallaHex": "88", "planta": 0, "guillermoPosX": 129, "guillermoPosY": 134, "bonus": 0, "porcentaje": 0}, {"name": "DecrObsequium", "des": "Obsequium 15 Decr -2", "reward": -0.006, "totalReward": -0.011099999999999995, "version": 1, "timestamp": "2019-03-23 11:37:11.003596", "numDia": 1, "momentoDia": 4, "obsequium": 15, "numPantalla": 21, "pantallaHex": "88", "planta": 0, "guillermoPosX": 129, "guillermoPosY": 134, "bonus": 0, "porcentaje": 0}, {"name": "DecrObsequium", "des": "Obsequium 13 Decr -2", "reward": -0.006, "totalReward": -0.014599999999999991, "version": 1, "timestamp": "2019-03-23 11:37:12.355335", "numDia": 1, "momentoDia": 4, "obsequium": 13, "numPantalla": 21, "pantallaHex": "88", "planta": 0, "guillermoPosX": 129, "guillermoPosY": 134, "bonus": 0, "porcentaje": 0}, {"name": "DecrObsequium", "des": "Obsequium 11 Decr -2", "reward": -0.006, "totalReward": -0.019299999999999987, "version": 1, "timestamp": "2019-03-23 11:37:13.746594", "numDia": 1, "momentoDia": 4, "obsequium": 11, "numPantalla": 21, "pantallaHex": "88", "planta": 0, "guillermoPosX": 129, "guillermoPosY": 134, "bonus": 0, "porcentaje": 0}, {"name": "DecrObsequium", "des": "Obsequium 9 Decr -2", "reward": -0.006, "totalReward": -0.023999999999999983, "version": 1, "timestamp": "2019-03-23 11:37:15.028110", "numDia": 1, "momentoDia": 4, "obsequium": 9, "numPantalla": 21, "pantallaHex": "88", "planta": 0, "guillermoPosX": 130, "guillermoPosY": 134, "bonus": 0, "porcentaje": 0}, {"name": "DecrObsequium", "des": "Obsequium 7 Decr -2", "reward": -0.006, "totalReward": -0.02939999999999998, "version": 1, "timestamp": "2019-03-23 11:37:15.812771", "numDia": 1, "momentoDia": 4, "obsequium": 7, "numPantalla": 21, "pantallaHex": "88", "planta": 0, "guillermoPosX": 130, "guillermoPosY": 133, "bonus": 0, "porcentaje": 0}, {"name": "DecrObsequium", "des": "Obsequium 5 Decr -2", "reward": -0.006, "totalReward": -0.0352, "version": 1, "timestamp": "2019-03-23 11:37:17.003430", "numDia": 1, "momentoDia": 4, "obsequium": 5, "numPantalla": 21, "pantallaHex": "88", "planta": 0, "guillermoPosX": 129, "guillermoPosY": 134, "bonus": 0, "porcentaje": 0}, {"name": "DecrObsequium", "des": "Obsequium 3 Decr -2", "reward": -0.006, "totalReward": -0.039800000000000016, "version": 1, "timestamp": "2019-03-23 11:37:18.271172", "numDia": 1, "momentoDia": 4, "obsequium": 3, "numPantalla": 21, "pantallaHex": "88", "planta": 0, "guillermoPosX": 129, "guillermoPosY": 134, "bonus": 0, "porcentaje": 0}, {"name": "DecrObsequium", "des": "Obsequium 1 Decr -1", "reward": -0.003, "totalReward": -0.044600000000000035, "version": 1, "timestamp": "2019-03-23 11:37:19.829940", "numDia": 1, "momentoDia": 4, "obsequium": 1, "numPantalla": 21, "pantallaHex": "88", "planta": 0, "guillermoPosX": 129, "guillermoPosY": 134, "bonus": 0, "porcentaje": 0}]}]
