[{"gameId":"190324_222722_717330", "totalSteps":646, "obsequium":0, "porcentaje":0, "bonus":0, "totalReward": "-1.0663", "events":[{"name": "NewRoom", "des": "prev 23 curr 22", "reward": 0.001, "totalReward": 0.005399999999999999, "version": 1, "timestamp": "2019-03-24 22:27:50.646773", "numDia": 1, "momentoDia": 4, "obsequium": 31, "numPantalla": 23, "pantallaHex": "89", "planta": 0, "guillermoPosX": 133, "guillermoPosY": 159, "bonus": 0, "porcentaje": 0}, {"name": "NewRoom", "des": "prev 22 curr 21", "reward": 0.001, "totalReward": 0.006300000000000139, "version": 1, "timestamp": "2019-03-24 22:28:23.682342", "numDia": 1, "momentoDia": 4, "obsequium": 31, "numPantalla": 22, "pantallaHex": "88", "planta": 0, "guillermoPosX": 135, "guillermoPosY": 143, "bonus": 0, "porcentaje": 0}, {"name": "DecrObsequium", "des": "Obsequium 31 Decr -2", "reward": -0.006, "totalReward": 0.009900000000000141, "version": 1, "timestamp": "2019-03-24 22:28:24.963357", "numDia": 1, "momentoDia": 4, "obsequium": 31, "numPantalla": 21, "pantallaHex": "88", "planta": 0, "guillermoPosX": 134, "guillermoPosY": 141, "bonus": 0, "porcentaje": 0}, {"name": "DecrObsequium", "des": "Obsequium 29 Decr -2", "reward": -0.006, "totalReward": 0.004000000000000139, "version": 1, "timestamp": "2019-03-24 22:28:26.280012", "numDia": 1, "momentoDia": 4, "obsequium": 29, "numPantalla": 21, "pantallaHex": "88", "planta": 0, "guillermoPosX": 130, "guillermoPosY": 141, "bonus": 0, "porcentaje": 0}, {"name": "DecrObsequium", "des": "Obsequium 27 Decr -2", "reward": -0.006, "totalReward": -0.0015999999999998615, "version": 1, "timestamp": "2019-03-24 22:28:27.232984", "numDia": 1, "momentoDia": 4, "obsequium": 27, "numPantalla": 21, "pantallaHex": "88", "planta": 0, "guillermoPosX": 130, "guillermoPosY": 137, "bonus": 0, "porcentaje": 0}, {"name": "DecrObsequium", "des": "Obsequium 25 Decr -2", "reward": -0.006, "totalReward": -0.008599999999999858, "version": 1, "timestamp": "2019-03-24 22:28:28.472284", "numDia": 1, "momentoDia": 4, "obsequium": 25, "numPantalla": 21, "pantallaHex": "88", "planta": 0, "guillermoPosX": 130, "guillermoPosY": 137, "bonus": 0, "porcentaje": 0}, {"name": "DecrObsequium", "des": "Obsequium 23 Decr -2", "reward": -0.006, "totalReward": -0.015399999999999853, "version": 1, "timestamp": "2019-03-24 22:28:29.574334", "numDia": 1, "momentoDia": 4, "obsequium": 23, "numPantalla": 21, "pantallaHex": "88", "planta": 0, "guillermoPosX": 130, "guillermoPosY": 138, "bonus": 0, "porcentaje": 0}, {"name": "NewRoom", "des": "prev 21 curr 20", "reward": 0.001, "totalReward": -0.02179999999999985, "version": 1, "timestamp": "2019-03-24 22:28:30.932310", "numDia": 1, "momentoDia": 4, "obsequium": 21, "numPantalla": 21, "pantallaHex": "78", "planta": 0, "guillermoPosX": 127, "guillermoPosY": 138, "bonus": 0, "porcentaje": 0}, {"name": "DecrObsequium", "des": "Obsequium 21 Decr -2", "reward": -0.006, "totalReward": -0.018399999999999847, "version": 1, "timestamp": "2019-03-24 22:28:32.368256", "numDia": 1, "momentoDia": 4, "obsequium": 21, "numPantalla": 20, "pantallaHex": "78", "planta": 0, "guillermoPosX": 125, "guillermoPosY": 138, "bonus": 0, "porcentaje": 0}, {"name": "DecrObsequium", "des": "Obsequium 19 Decr -2", "reward": -0.006, "totalReward": -0.02519999999999984, "version": 1, "timestamp": "2019-03-24 22:28:33.464029", "numDia": 1, "momentoDia": 4, "obsequium": 19, "numPantalla": 20, "pantallaHex": "78", "planta": 0, "guillermoPosX": 121, "guillermoPosY": 141, "bonus": 0, "porcentaje": 0}, {"name": "DecrObsequium", "des": "Obsequium 17 Decr -2", "reward": -0.006, "totalReward": -0.03229999999999987, "version": 1, "timestamp": "2019-03-24 22:28:34.835569", "numDia": 1, "momentoDia": 4, "obsequium": 17, "numPantalla": 20, "pantallaHex": "78", "planta": 0, "guillermoPosX": 116, "guillermoPosY": 140, "bonus": 0, "porcentaje": 0}, {"name": "DecrObsequium", "des": "Obsequium 15 Decr -2", "reward": -0.006, "totalReward": -0.03799999999999989, "version": 1, "timestamp": "2019-03-24 22:28:36.029037", "numDia": 1, "momentoDia": 4, "obsequium": 15, "numPantalla": 20, "pantallaHex": "78", "planta": 0, "guillermoPosX": 119, "guillermoPosY": 138, "bonus": 0, "porcentaje": 0}, {"name": "DecrObsequium", "des": "Obsequium 13 Decr -2", "reward": -0.006, "totalReward": -0.04419999999999992, "version": 1, "timestamp": "2019-03-24 22:28:37.589562", "numDia": 1, "momentoDia": 4, "obsequium": 13, "numPantalla": 20, "pantallaHex": "78", "planta": 0, "guillermoPosX": 116, "guillermoPosY": 138, "bonus": 0, "porcentaje": 0}, {"name": "DecrObsequium", "des": "Obsequium 11 Decr -2", "reward": -0.006, "totalReward": -0.04939999999999995, "version": 1, "timestamp": "2019-03-24 22:28:39.376172", "numDia": 1, "momentoDia": 4, "obsequium": 11, "numPantalla": 20, "pantallaHex": "78", "planta": 0, "guillermoPosX": 120, "guillermoPosY": 138, "bonus": 0, "porcentaje": 0}, {"name": "DecrObsequium", "des": "Obsequium 9 Decr -2", "reward": -0.006, "totalReward": -0.052099999999999966, "version": 1, "timestamp": "2019-03-24 22:28:40.680788", "numDia": 1, "momentoDia": 4, "obsequium": 9, "numPantalla": 20, "pantallaHex": "78", "planta": 0, "guillermoPosX": 121, "guillermoPosY": 139, "bonus": 0, "porcentaje": 0}, {"name": "DecrObsequium", "des": "Obsequium 7 Decr -2", "reward": -0.006, "totalReward": -0.05709999999999999, "version": 1, "timestamp": "2019-03-24 22:28:42.313914", "numDia": 1, "momentoDia": 4, "obsequium": 7, "numPantalla": 20, "pantallaHex": "78", "planta": 0, "guillermoPosX": 121, "guillermoPosY": 137, "bonus": 0, "porcentaje": 0}, {"name": "DecrObsequium", "des": "Obsequium 5 Decr -2", "reward": -0.006, "totalReward": -0.062100000000000016, "version": 1, "timestamp": "2019-03-24 22:28:43.814416", "numDia": 1, "momentoDia": 4, "obsequium": 5, "numPantalla": 20, "pantallaHex": "78", "planta": 0, "guillermoPosX": 123, "guillermoPosY": 139, "bonus": 0, "porcentaje": 0}, {"name": "NewRoom", "des": "prev 20 curr 21", "reward": 0.001, "totalReward": -0.06890000000000004, "version": 1, "timestamp": "2019-03-24 22:28:45.682553", "numDia": 1, "momentoDia": 4, "obsequium": 3, "numPantalla": 20, "pantallaHex": "88", "planta": 0, "guillermoPosX": 128, "guillermoPosY": 141, "bonus": 0, "porcentaje": 0}, {"name": "NewRoom", "des": "prev 21 curr 20", "reward": 0.001, "totalReward": -0.06510000000000005, "version": 1, "timestamp": "2019-03-24 22:28:47.346504", "numDia": 1, "momentoDia": 4, "obsequium": 3, "numPantalla": 21, "pantallaHex": "78", "planta": 0, "guillermoPosX": 127, "guillermoPosY": 140, "bonus": 0, "porcentaje": 0}, {"name": "DecrObsequium", "des": "Obsequium 3 Decr -2", "reward": -0.006, "totalReward": -0.06110000000000004, "version": 1, "timestamp": "2019-03-24 22:28:47.881699", "numDia": 1, "momentoDia": 4, "obsequium": 3, "numPantalla": 20, "pantallaHex": "78", "planta": 0, "guillermoPosX": 125, "guillermoPosY": 140, "bonus": 0, "porcentaje": 0}, {"name": "DecrObsequium", "des": "Obsequium 1 Decr -1", "reward": -0.003, "totalReward": -0.06470000000000006, "version": 1, "timestamp": "2019-03-24 22:28:48.968045", "numDia": 1, "momentoDia": 4, "obsequium": 1, "numPantalla": 20, "pantallaHex": "78", "planta": 0, "guillermoPosX": 125, "guillermoPosY": 137, "bonus": 0, "porcentaje": 0}]}]
[{"gameId":"190324_222722_717330", "totalSteps":646, "obsequium":0, "porcentaje":0, "bonus":0, "totalReward": "-1.0663", "events":[{"name": "NewRoom", "des": "prev 23 curr 22", "reward": 0.001, "totalReward": 0.005399999999999999, "version": 1, "timestamp": "2019-03-24 22:27:50.646773", "numDia": 1, "momentoDia": 4, "obsequium": 31, "numPantalla": 23, "pantallaHex": "89", "planta": 0, "guillermoPosX": 133, "guillermoPosY": 159, "bonus": 0, "porcentaje": 0}, {"name": "NewRoom", "des": "prev 22 curr 21", "reward": 0.001, "totalReward": 0.006300000000000139, "version": 1, "timestamp": "2019-03-24 22:28:23.682342", "numDia": 1, "momentoDia": 4, "obsequium": 31, "numPantalla": 22, "pantallaHex": "88", "planta": 0, "guillermoPosX": 135, "guillermoPosY": 143, "bonus": 0, "porcentaje": 0}, {"name": "DecrObsequium", "des": "Obsequium 31 Decr -2", "reward": -0.006, "totalReward": 0.009900000000000141, "version": 1, "timestamp": "2019-03-24 22:28:24.963357", "numDia": 1, "momentoDia": 4, "obsequium": 31, "numPantalla": 21, "pantallaHex": "88", "planta": 0, "guillermoPosX": 134, "guillermoPosY": 141, "bonus": 0, "porcentaje": 0}, {"name": "DecrObsequium", "des": "Obsequium 29 Decr -2", "reward": -0.006, "totalReward": 0.004000000000000139, "version": 1, "timestamp": "2019-03-24 22:28:26.280012", "numDia": 1, "momentoDia": 4, "obsequium": 29, "numPantalla": 21, "pantallaHex": "88", "planta": 0, "guillermoPosX": 130, "guillermoPosY": 141, "bonus": 0, "porcentaje": 0}, {"name": "DecrObsequium", "des": "Obsequium 27 Decr -2", "reward": -0.006, "totalReward": -0.0015999999999998615, "version": 1, "timestamp": "2019-03-24 22:28:27.232984", "numDia": 1, "momentoDia": 4, "obsequium": 27, "numPantalla": 21, "pantallaHex": "88", "planta": 0, "guillermoPosX": 130, "guillermoPosY": 137, "bonus": 0, "porcentaje": 0}, {"name": "DecrObsequium", "des": "Obsequium 25 Decr -2", "reward": -0.006, "totalReward": -0.008599999999999858, "version": 1, "timestamp": "2019-03-24 22:28:28.472284", "numDia": 1, "momentoDia": 4, "obsequium": 25, "numPantalla": 21, "pantallaHex": "88", "planta": 0, "guillermoPosX": 130, "guillermoPosY": 137, "bonus": 0, "porcentaje": 0}, {"name": "DecrObsequium", "des": "Obsequium 23 Decr -2", "reward": -0.006, "totalReward": -0.015399999999999853, "version": 1, "timestamp": "2019-03-24 22:28:29.574334", "numDia": 1, "momentoDia": 4, "obsequium": 23, "numPantalla": 21, "pantallaHex": "88", "planta": 0, "guillermoPosX": 130, "guillermoPosY": 138, "bonus": 0, "porcentaje": 0}, {"name": "NewRoom", "des": "prev 21 curr 20", "reward": 0.001, "totalReward": -0.02179999999999985, "version": 1, "timestamp": "2019-03-24 22:28:30.932310", "numDia": 1, "momentoDia": 4, "obsequium": 21, "numPantalla": 21, "pantallaHex": "78", "planta": 0, "guillermoPosX": 127, "guillermoPosY": 138, "bonus": 0, "porcentaje": 0}, {"name": "DecrObsequium", "des": "Obsequium 21 Decr -2", "reward": -0.006, "totalReward": -0.018399999999999847, "version": 1, "timestamp": "2019-03-24 22:28:32.368256", "numDia": 1, "momentoDia": 4, "obsequium": 21, "numPantalla": 20, "pantallaHex": "78", "planta": 0, "guillermoPosX": 125, "guillermoPosY": 138, "bonus": 0, "porcentaje": 0}, {"name": "DecrObsequium", "des": "Obsequium 19 Decr -2", "reward": -0.006, "totalReward": -0.02519999999999984, "version": 1, "timestamp": "2019-03-24 22:28:33.464029", "numDia": 1, "momentoDia": 4, "obsequium": 19, "numPantalla": 20, "pantallaHex": "78", "planta": 0, "guillermoPosX": 121, "guillermoPosY": 141, "bonus": 0, "porcentaje": 0}, {"name": "DecrObsequium", "des": "Obsequium 17 Decr -2", "reward": -0.006, "totalReward": -0.03229999999999987, "version": 1, "timestamp": "2019-03-24 22:28:34.835569", "numDia": 1, "momentoDia": 4, "obsequium": 17, "numPantalla": 20, "pantallaHex": "78", "planta": 0, "guillermoPosX": 116, "guillermoPosY": 140, "bonus": 0, "porcentaje": 0}, {"name": "DecrObsequium", "des": "Obsequium 15 Decr -2", "reward": -0.006, "totalReward": -0.03799999999999989, "version": 1, "timestamp": "2019-03-24 22:28:36.029037", "numDia": 1, "momentoDia": 4, "obsequium": 15, "numPantalla": 20, "pantallaHex": "78", "planta": 0, "guillermoPosX": 119, "guillermoPosY": 138, "bonus": 0, "porcentaje": 0}, {"name": "DecrObsequium", "des": "Obsequium 13 Decr -2", "reward": -0.006, "totalReward": -0.04419999999999992, "version": 1, "timestamp": "2019-03-24 22:28:37.589562", "numDia": 1, "momentoDia": 4, "obsequium": 13, "numPantalla": 20, "pantallaHex": "78", "planta": 0, "guillermoPosX": 116, "guillermoPosY": 138, "bonus": 0, "porcentaje": 0}, {"name": "DecrObsequium", "des": "Obsequium 11 Decr -2", "reward": -0.006, "totalReward": -0.04939999999999995, "version": 1, "timestamp": "2019-03-24 22:28:39.376172", "numDia": 1, "momentoDia": 4, "obsequium": 11, "numPantalla": 20, "pantallaHex": "78", "planta": 0, "guillermoPosX": 120, "guillermoPosY": 138, "bonus": 0, "porcentaje": 0}, {"name": "DecrObsequium", "des": "Obsequium 9 Decr -2", "reward": -0.006, "totalReward": -0.052099999999999966, "version": 1, "timestamp": "2019-03-24 22:28:40.680788", "numDia": 1, "momentoDia": 4, "obsequium": 9, "numPantalla": 20, "pantallaHex": "78", "planta": 0, "guillermoPosX": 121, "guillermoPosY": 139, "bonus": 0, "porcentaje": 0}, {"name": "DecrObsequium", "des": "Obsequium 7 Decr -2", "reward": -0.006, "totalReward": -0.05709999999999999, "version": 1, "timestamp": "2019-03-24 22:28:42.313914", "numDia": 1, "momentoDia": 4, "obsequium": 7, "numPantalla": 20, "pantallaHex": "78", "planta": 0, "guillermoPosX": 121, "guillermoPosY": 137, "bonus": 0, "porcentaje": 0}, {"name": "DecrObsequium", "des": "Obsequium 5 Decr -2", "reward": -0.006, "totalReward": -0.062100000000000016, "version": 1, "timestamp": "2019-03-24 22:28:43.814416", "numDia": 1, "momentoDia": 4, "obsequium": 5, "numPantalla": 20, "pantallaHex": "78", "planta": 0, "guillermoPosX": 123, "guillermoPosY": 139, "bonus": 0, "porcentaje": 0}, {"name": "NewRoom", "des": "prev 20 curr 21", "reward": 0.001, "totalReward": -0.06890000000000004, "version": 1, "timestamp": "2019-03-24 22:28:45.682553", "numDia": 1, "momentoDia": 4, "obsequium": 3, "numPantalla": 20, "pantallaHex": "88", "planta": 0, "guillermoPosX": 128, "guillermoPosY": 141, "bonus": 0, "porcentaje": 0}, {"name": "NewRoom", "des": "prev 21 curr 20", "reward": 0.001, "totalReward": -0.06510000000000005, "version": 1, "timestamp": "2019-03-24 22:28:47.346504", "numDia": 1, "momentoDia": 4, "obsequium": 3, "numPantalla": 21, "pantallaHex": "78", "planta": 0, "guillermoPosX": 127, "guillermoPosY": 140, "bonus": 0, "porcentaje": 0}, {"name": "DecrObsequium", "des": "Obsequium 3 Decr -2", "reward": -0.006, "totalReward": -0.06110000000000004, "version": 1, "timestamp": "2019-03-24 22:28:47.881699", "numDia": 1, "momentoDia": 4, "obsequium": 3, "numPantalla": 20, "pantallaHex": "78", "planta": 0, "guillermoPosX": 125, "guillermoPosY": 140, "bonus": 0, "porcentaje": 0}, {"name": "DecrObsequium", "des": "Obsequium 1 Decr -1", "reward": -0.003, "totalReward": -0.06470000000000006, "version": 1, "timestamp": "2019-03-24 22:28:48.968045", "numDia": 1, "momentoDia": 4, "obsequium": 1, "numPantalla": 20, "pantallaHex": "78", "planta": 0, "guillermoPosX": 125, "guillermoPosY": 137, "bonus": 0, "porcentaje": 0}]}]
